sps30/__init__.py
sps30/sps30.py
sps30-0.1.10.data/scripts/run-sps30
sps30-0.1.10.dist-info/LICENSE
sps30-0.1.10.dist-info/METADATA
sps30-0.1.10.dist-info/WHEEL
sps30-0.1.10.dist-info/top_level.txt
sps30-0.1.10.dist-info/RECORD
