Metadata-Version: 2.1
Name: sps30
Version: 0.1.10
Summary: Python3 I2C Driver & Application for SPS30 PM Sensor
Home-page: https://github.com/feyzikesim/sps30
Author: Feyzi Kesim
Author-email: feyzikesim@gmail.com
License: UNKNOWN
Platform: UNKNOWN
Classifier: Programming Language :: Python :: 3
Classifier: License :: OSI Approved :: MIT License
Classifier: Operating System :: OS Independent
Requires-Python: >=3.6
